label_studio_brush_rle_rs-0.1.1.dist-info/METADATA
label_studio_brush_rle_rs-0.1.1.dist-info/WHEEL
label_studio_brush_rle_rs/__init__.py
label_studio_brush_rle_rs/label_studio_brush_rle_rs.cpython-312-x86_64-linux-gnu.so
label_studio_brush_rle_rs-0.1.1.dist-info/RECORD
