Metadata-Version: 2.4
Name: label-studio-brush-rle-rs
Version: 0.1.1
Classifier: Programming Language :: Rust
Classifier: Programming Language :: Python :: Implementation :: CPython
Classifier: Programming Language :: Python :: Implementation :: PyPy
Requires-Dist: numpy>=1.24.4,<3.0.0
Summary: Rust implementation of run-length encoding for brush masks in Label Studio for speed.
Author: teepoy
Requires-Python: >=3.8
Project-URL: Homepage, https://github.com/teepoy/label-studio-brush-rle-rs
Project-URL: Repository, https://github.com/teepoy/label-studio-brush-rle-rs
